Workbook

Sheet Assumptions
A1: Northwind Industrial - DCF assumptions ($ millions)
A3: Revenue growth | B3: 0.06
A4: EBIT margin | B4: 0.15
A5: Tax rate | B5: 0.25
A6: D&A (% of revenue) | B6: 0.04
A7: Capex (% of revenue) | B7: 0.05
A8: Net working capital (% of revenue) | B8: 0.12
A9: WACC | B9: 0.08
A10: Terminal growth | B10: 0.06
A11: Net debt | B11: 300
A12: Shares outstanding (m) | B12: 50

Sheet DCF
A2: Period | C2: 1 | D2: 2 | E2: 3 | F2: 4 | G2: 5
A3: ($ millions) | B3: 2023A | C3: 2024E | D3: 2025E | E3: 2026E | F3: 2027E | G3: 2028E
A4: Revenue | B4: 1000 | C4: =B4*(1+Assumptions!$B$3) -> 1060 | D4: =C4*(1+Assumptions!$B$3) -> 1123.6 | E4: =D4*1.06 -> 1191.016 | F4: =E4*(1+Assumptions!$B$3) -> 1262.477 | G4: =F4*(1+Assumptions!$B$3) -> 1338.2256
A5: EBIT | C5: =C4*Assumptions!$B$4 -> 159 | D5: =D4*Assumptions!$B$4 -> 168.54 | E5: =E4*Assumptions!$B$4 -> 178.6524 | F5: 180 | G5: =G4*Assumptions!$B$4 -> 200.73384
A6: Taxes on EBIT | C6: =C5*Assumptions!$B$5 -> 39.75 | D6: =D5*Assumptions!$B$5 -> 42.135 | E6: =E5*Assumptions!$B$5 -> 44.6631 | F6: =F5*Assumptions!$B$5 -> 45 | G6: =G5*Assumptions!$B$5 -> 50.183459
A7: NOPAT | C7: =C5-C6 -> 119.25 | D7: =D5-D6 -> 126.405 | E7: =E5-E6 -> 133.9893 | F7: =F5-F6 -> 135 | G7: =G5-G6 -> 150.55038
A8: Depreciation & amortization | C8: =C4*Assumptions!$B$6 -> 42.4 | D8: =D4*Assumptions!$B$6 -> 44.944 | E8: =E4*Assumptions!$B$6 -> 47.64064 | F8: =F4*Assumptions!$B$6 -> 50.499078 | G8: =G4*Assumptions!$B$6 -> 53.529023
A9: Capital expenditures | C9: =C4*Assumptions!$B$7 -> 53 | D9: =D4*Assumptions!$B$7 -> 56.18 | E9: =E4*Assumptions!$B$7 -> 59.5508 | F9: =F4*Assumptions!$B$7 -> 63.123848 | G9: =G4*Assumptions!$B$7 -> 66.911279
A10: Net working capital | B10: 120 | C10: =C4*Assumptions!$B$8 -> 127.2 | D10: =D4*Assumptions!$B$8 -> 134.832 | E10: =E4*Assumptions!$B$8 -> 142.92192 | F10: =F4*Assumptions!$B$8 -> 151.49724 | G10: =G4*Assumptions!$B$8 -> 160.58707
A11: Change in NWC | C11: =C10-B10 -> 7.2 | D11: =D10-C10 -> 7.632 | E11: =E10-D10 -> 8.08992 | F11: =F10-E10 -> 8.5753152 | G11: =G10-F10 -> 9.0898341
A12: Free cash flow to firm | C12: =C5+C8-C9-C11 -> 141.2 | D12: =D5+D8-D9-D11 -> 149.672 | E12: =E5+E8-E9 -> 166.74224 | F12: =F5+F8-F9-F11 -> 158.79992 | G12: =G5+G8-G9-G11 -> 178.26175
A13: Discount factor | C13: =1/(1+Assumptions!$B$9)^C2 -> 0.92592593 | D13: =1/(1+Assumptions!$B$9)^D2 -> 0.85733882 | E13: =1/(1+Assumptions!$B$9)^E2 -> 0.79383224 | F13: =1/(1+Assumptions!$B$9)^F2 -> 0.73502985 | G13: =1/(1+Assumptions!$B$9)^G2 -> 0.6805832
A14: PV of FCFF | C14: =C12*C13 -> 130.74074 | D14: =D12*D13 -> 128.31962 | E14: =E12*E13 -> 132.36537 | F14: =F12*F13 -> 116.72268 | G14: =G12*G13 -> 121.32195
A16: Sum of PV of FCFF | B16: =SUM(C14:G14) -> 629.47035
A17: Terminal value | B17: =G12*(1+Assumptions!$B$10)/(Assumptions!$B$9-Assumptions!$B$10) -> 9447.8726
A18: PV of terminal value | B18: =B17/(1+Assumptions!$B$9)^4 -> 6944.4684
A19: Enterprise value | B19: =B16+B18 -> 7573.9387
A20: Net debt | B20: =Assumptions!$B$11 -> 300
A21: Equity value | B21: =B19-B20 -> 7273.9387
A22: Value per share ($) | B22: =B21/Assumptions!$B$12 -> 145.47877

Sheet WACC
A2: Risk-free rate | B2: 0.04
A3: Equity beta | B3: 1.2
A4: Equity risk premium | B4: 0.055
A5: Pre-tax cost of debt | B5: 0.06
A6: Share price ($) | B6: 30
A7: Equity (book value) | B7: 400
A8: Debt (book value) | B8: 350
A10: Cost of equity (CAPM) | B10: =B2+B3*B4 -> 0.106
A11: Weight of equity | B11: =B7/(B7+B8) -> 0.53333333
A12: Weight of debt | B12: =B8/(B7+B8) -> 0.46666667
A13: WACC (computed) | B13: =B11*B10+B12*B5*(1-Assumptions!$B$5) -> 0.077533333

Sheet BS
A1: Balance sheet ($ millions)
B2: 2021A | C2: 2022A | D2: 2023A
A3: Cash | B3: 80 | C3: 95 | D3: 110
A4: Receivables | B4: 150 | C4: 160 | D4: 170
A5: Inventory | B5: 120 | C5: 130 | D5: 140
A6: PP&E, net | B6: 520 | C6: 520 | D6: 540
A7: Total assets | B7: =SUM(B3:B6) -> 870 | C7: =SUM(C3:C6) -> 905 | D7: =SUM(D3:D6) -> 960
A8: Payables | B8: 90 | C8: 95 | D8: 100
A9: Long-term debt | B9: 400 | C9: 405 | D9: 410
A10: Total liabilities | B10: =B8+B9 -> 490 | C10: =C8+C9 -> 500 | D10: =D8+D9 -> 510
A11: Total equity | B11: 380 | C11: 400 | D11: 450
A12: Total liabilities and equity | B12: =B10+B11 -> 870 | C12: =C10+C11 -> 900 | D12: =D10+D11 -> 960
